src/playwright_server/__init__.py
src/playwright_server/server.py
orange_playwright_server-0.1.0.dist-info/METADATA
orange_playwright_server-0.1.0.dist-info/WHEEL
orange_playwright_server-0.1.0.dist-info/entry_points.txt
orange_playwright_server-0.1.0.dist-info/licenses/LICENSE
orange_playwright_server-0.1.0.dist-info/RECORD
