Metadata-Version: 2.4
Name: orange-playwright-server
Version: 0.1.0
Summary: \A MCP server with playwright tools\
Author-email: YUNYING <qcyunying@gmail.com>
License-File: LICENSE
Requires-Python: >=3.11
Requires-Dist: mcp>=1.1.2
Requires-Dist: playwright
